openai_harmony-0.0.8.dist-info/METADATA
openai_harmony-0.0.8.dist-info/WHEEL
openai_harmony-0.0.8.dist-info/licenses/LICENSE
openai_harmony/__init__.py
openai_harmony/openai_harmony.abi3.so
openai_harmony-0.0.8.dist-info/RECORD
