Metadata-Version: 2.4
Name: openai-harmony
Version: 0.0.8
Classifier: Programming Language :: Rust
Classifier: Programming Language :: Python :: Implementation :: CPython
Classifier: Programming Language :: Python :: Implementation :: PyPy
Requires-Dist: pydantic>=2.11.7
Requires-Dist: uvicorn ; extra == 'demo'
Requires-Dist: fastapi ; extra == 'demo'
Provides-Extra: demo
License-File: LICENSE
Summary: OpenAI's response format for its open-weight model series gpt-oss
Requires-Python: >=3.8
